vintageconsoleinfo/__init__.py
vintageconsoleinfo/main.py
vintageconsoleinfo/prompts.py
vintageconsoleinfo-2025.12.21163636.dist-info/METADATA
vintageconsoleinfo-2025.12.21163636.dist-info/WHEEL
vintageconsoleinfo-2025.12.21163636.dist-info/top_level.txt
vintageconsoleinfo-2025.12.21163636.dist-info/RECORD
