Metadata-Version: 2.4
Name: vintageconsoleinfo
Version: 2025.12.21163636
Summary: The system is designed to process user descriptions or inputs related to vintage gaming consoles, such as the Interton Video Computer 4000, and generate structured summaries or specifications. It focu
Author-email: vintageconsoleinfo <hi@eugene.plus>
License: MIT
Project-URL: Homepage, https://github.com/chigwell/vintageconsoleinfo
Requires-Python: >=3.9
Requires-Dist: langchain-llm7>=0.0.0
Requires-Dist: llmatch-messages>=0.0.0
Requires-Dist: langchain-core>=0.3.0
